log_check.py
log_check-2.3.0.dist-info/METADATA
log_check-2.3.0.dist-info/WHEEL
log_check-2.3.0.dist-info/entry_points.txt
log_check-2.3.0.dist-info/top_level.txt
log_check-2.3.0.dist-info/RECORD
