Metadata-Version: 2.1
Name: log-check
Version: 2.3.0
Summary: LOG 检查工具
Home-page: https://gitlab.gz.cvte.cn/i_guozhihou/log_check
Author: ice_summer
Author-email: 2053620282@qq.com
License: MIT
Classifier: Programming Language :: Python :: 3
